[
  {
    "Device Id": "83dd0ad6503297d0", 
    "username": "Mohammad",
    "password": "1122",
    "expiry": "2028-10-15"
  },
  {
    "Device Id": "cffa456d092ef16d",
    "username": "اسماعیل",
    "password": "cffa456d092ef16d",
    "expiry": "2028-10-15"
  },
  {
    "Device Id": "❌",
    "username": "❌",
    "password": "❌",
    "expiry": "2028-10-15"
  },
  {
    "Device Id": "✅",
    "username": "الله نظر",
    "password": "✅",
    "expiry": "2028-10-15"
  },
  {
    "Device Id": "❌",
    "username": "❌",
    "password": "❌",
    "expiry": "2028-10-15"
  },
  {
    "Device Id": "❌",
    "username": "❌",
    "password": "❌",
    "expiry": "2028-10-15"
  },
  {
    "Device Id": "❌",
    "username": "❌",
    "password": "❌",
    "expiry": "2028-10-15"
  },
  {
    "Device Id": "❌", 
    "username": "❌",
    "password": "❌",
    "expiry": "2028-10-15"
  },
  {
    "Device Id": "❌",
    "username": "❌",
    "password": "❌",
    "expiry": "2028-10-15"
  },
  {
    "Device Id": "❌",
    "username": "❌",
    "password": "❌",
    "expiry": "2028-10-15"
  },
  {
    "Device Id": "❌",
    "username": "❌",
    "password": "❌",
    "expiry": "2028-10-15"
  },
  {
    "Device Id": "❌",
    "username": "ا❌",
    "password": "❌",
    "expiry": "2028-10-15"
  },
  {
    "Device Id": "❌",
    "username": "❌",
    "password": "❌",
    "expiry": "2028-10-15"
  },
  {
    "Device Id": "❌",
    "username": "❌",
    "password": "❌",
    "expiry": "2028-10-15"
  },
  {
    "Device Id": "❌", 
    "username": "❌",
    "password": "❌❌",
    "expiry": "2028-10-15"
  },
  {
    "Device Id": "❌",
    "username": "❌",
    "password": "❌",
    "expiry": "2028-10-15"
  },
  {
    "Device Id": "❌",
    "username": "❌",
    "password": "❌",
    "expiry": "2028-10-15"
  },
  {
    "Device Id": "❌",
    "username": "❌",
    "password": "❌",
    "expiry": "2028-10-15"
  },
  {
    "Device Id": "PASTE-DEVICE-ID",
    "username": "jkl",
    "password": "104",
    "expiry": "2028-10-15"
  },
  {
    "Device Id": "PASTE-DEVICE-ID",
    "username": "mno",
    "password": "105",
    "expiry": "2028-10-15"
  },
  {
    "Device Id": "PASTE-DEVICE-ID",
    "username": "pqr",
    "password": "106",
    "expiry": "2028-10-15"
  },
  {
    "Device Id": "PASTE-DEVICE-ID", 
    "username": "PASTE-USERNAME",
    "password": "PASTE-PASSWORD",
    "expiry": "2028-10-15"
  },
  {
    "Device Id": "jonohit",
    "username": "abc",
    "password": "101",
    "expiry": "2028-10-15"
  },
  {
    "Device Id": "PASTE-DEVICE-ID",
    "username": "def",
    "password": "102",
    "expiry": "2028-10-15"
  },
  {
    "Device Id": "PASTE-DEVICE-ID",
    "username": "ghi",
    "password": "103",
    "expiry": "2028-10-15"
  },
  {
    "Device Id": "PASTE-DEVICE-ID",
    "username": "jkl",
    "password": "104",
    "expiry": "2028-10-15"
  },
  {
    "Device Id": "PASTE-DEVICE-ID",
    "username": "mno",
    "password": "105",
    "expiry": "2028-10-15"
  },
  {
    "Device Id": "PASTE-DEVICE-ID",
    "username": "pqr",
    "password": "106",
    "expiry": "2028-10-15"
  }
]
